pytroll_collectors/__init__.py
pytroll_collectors/config.py
pytroll_collectors/fsspec_to_message.py
pytroll_collectors/geographic_gatherer.py
pytroll_collectors/harvest_EUM_schedules.py
pytroll_collectors/helper_functions.py
pytroll_collectors/logging.py
pytroll_collectors/region_collector.py
pytroll_collectors/s3stalker.py
pytroll_collectors/s3stalker_daemon_runner.py
pytroll_collectors/scisys.py
pytroll_collectors/segments.py
pytroll_collectors/trollstalker.py
pytroll_collectors/utils.py
pytroll_collectors/version.py
pytroll_collectors/scripts/__init__.py
pytroll_collectors/scripts/cat.py
pytroll_collectors/scripts/geographic_gatherer.py
pytroll_collectors/scripts/s3stalker.py
pytroll_collectors/scripts/s3stalker_daemon.py
pytroll_collectors/scripts/scisys_receiver.py
pytroll_collectors/scripts/segment_gatherer.py
pytroll_collectors/scripts/trollstalker.py
pytroll_collectors/scripts/trollstalker2.py
pytroll_collectors/scripts/zipcollector_runner.py
pytroll_collectors/tests/__init__.py
pytroll_collectors/tests/conftest.py
pytroll_collectors/tests/test_config.py
pytroll_collectors/tests/test_fsspec_to_message.py
pytroll_collectors/tests/test_geographic_gatherer.py
pytroll_collectors/tests/test_harvest_EUM_schedules.py
pytroll_collectors/tests/test_helper_functions.py
pytroll_collectors/tests/test_region_collector.py
pytroll_collectors/tests/test_s3stalker.py
pytroll_collectors/tests/test_s3stalker_daemon_runner.py
pytroll_collectors/tests/test_scisys.py
pytroll_collectors/tests/test_segments.py
pytroll_collectors/tests/test_triggers.py
pytroll_collectors/tests/test_trollstalker.py
pytroll_collectors/tests/data/20161012_1200_EPSG4326_wv_no_blend.png
pytroll_collectors/tests/data/20161012_1200_GOES-13_EPSG4326_wv.png
pytroll_collectors/tests/data/20161012_1200_GOES-15_EPSG4326_wv.png
pytroll_collectors/tests/data/20161012_1200_Himawari-8_EPSG4326_wv.png
pytroll_collectors/tests/data/20161012_1200_Meteosat-10_EPSG4326_wv.png
pytroll_collectors-0.20.0.dist-info/METADATA
pytroll_collectors-0.20.0.dist-info/WHEEL
pytroll_collectors-0.20.0.dist-info/entry_points.txt
pytroll_collectors-0.20.0.dist-info/licenses/LICENSE
pytroll_collectors-0.20.0.dist-info/RECORD
