Metadata-Version: 2.4
Name: pytroll-collectors
Version: 0.20.0
Summary: Pytroll data collectors
Project-URL: Homepage, https://github.com/pytroll/pytroll-collectors
Author-email: Martin Raspaud <martin.raspaud@smhi.se>
License-Expression: GPL-3.0-or-later
License-File: LICENSE
Classifier: Development Status :: 3 - Alpha
Classifier: Intended Audience :: Science/Research
Classifier: Operating System :: OS Independent
Classifier: Programming Language :: Python
Classifier: Topic :: Scientific/Engineering
Requires-Python: >=3.11
Requires-Dist: posttroll>=1.3.0
Requires-Dist: pyyaml
Requires-Dist: trollsift
Provides-Extra: all
Requires-Dist: fsspec; extra == 'all'
Requires-Dist: netifaces; extra == 'all'
Requires-Dist: pyresample; extra == 'all'
Requires-Dist: python-dateutil; extra == 'all'
Requires-Dist: pytroll-schedule; extra == 'all'
Requires-Dist: s3fs; extra == 'all'
Requires-Dist: watchdog!=4.0.0; extra == 'all'
Provides-Extra: geographic-gatherer
Requires-Dist: pyresample; extra == 'geographic-gatherer'
Requires-Dist: pytroll-schedule; extra == 'geographic-gatherer'
Requires-Dist: watchdog!=4.0.0; extra == 'geographic-gatherer'
Provides-Extra: s3-segment-gatherer
Requires-Dist: fsspec; extra == 's3-segment-gatherer'
Provides-Extra: s3stalker
Requires-Dist: python-dateutil; extra == 's3stalker'
Requires-Dist: s3fs; extra == 's3stalker'
Provides-Extra: scisys-receiver
Requires-Dist: netifaces; extra == 'scisys-receiver'
Provides-Extra: trollstalker
Requires-Dist: watchdog!=4.0.0; extra == 'trollstalker'
